jhub_shibboleth_auth/__init__.py
jhub_shibboleth_auth/shibboleth_auth.py
jhub_shibboleth_auth/utils.py
jhub_shibboleth_auth-1.5.0.dist-info/LICENSE
jhub_shibboleth_auth-1.5.0.dist-info/METADATA
jhub_shibboleth_auth-1.5.0.dist-info/WHEEL
jhub_shibboleth_auth-1.5.0.dist-info/top_level.txt
jhub_shibboleth_auth-1.5.0.dist-info/RECORD
