Metadata-Version: 2.1
Name: jhub-shibboleth-auth
Version: 1.5.0
Summary: Shibboleth authentication for JupyterHub.
Home-page: https://github.com/gesiscss/jhub_shibboleth_auth
License: MIT
Project-URL: Bug Reports, https://github.com/gesiscss/jhub_shibboleth_auth/issues
Project-URL: Source, https://github.com/gesiscss/jhub_shibboleth_auth
Keywords: sshibboleth auth nginx jupyterhub
Platform: UNKNOWN
Classifier: Intended Audience :: Developers
Classifier: License :: OSI Approved :: MIT License
Classifier: Programming Language :: Python :: 3.5
Classifier: Programming Language :: Python :: 3.6
Requires-Dist: jupyterhub (==0.9.6)
